rygforms/__main__.py
rygforms/templates/error.htm
rygforms/templates/main.html
rygforms/templates/stampo.html
rygforms/validator.py
rygforms-0.5.12.dist-info/entry_points.txt
rygforms-0.5.12.dist-info/WHEEL
rygforms-0.5.12.dist-info/METADATA
rygforms-0.5.12.dist-info/RECORD
