Metadata-Version: 2.1
Name: rygforms
Version: 0.5.12
Summary: OAuth2 Login for Typeform and Tripetto
Home-page: https://forms.ryg.one/
License: AGPL-3.0-or-later
Keywords: oauth2,tripetto,typeform,flask,ryg
Author: Stefano Pigozzi
Author-email: me@steffo.eu
Maintainer: Stefano Pigozzi
Maintainer-email: me@steffo.eu
Requires-Python: >=3.7,<4.0
Classifier: License :: OSI Approved :: GNU Affero General Public License v3 or later (AGPLv3+)
Classifier: Programming Language :: Python :: 3
Classifier: Programming Language :: Python :: 3.10
Classifier: Programming Language :: Python :: 3.7
Classifier: Programming Language :: Python :: 3.8
Classifier: Programming Language :: Python :: 3.9
Requires-Dist: authlib (>=1.0.0,<2.0.0)
Requires-Dist: click (>=8.0.3,<9.0.0)
Requires-Dist: flask (>=2.0.3,<3.0.0)
Requires-Dist: gunicorn (>=20.1.0,<21.0.0)
Requires-Dist: itsdangerous (>=2.1.2,<3.0.0)
Requires-Dist: python-dotenv (>=0.15.0,<0.16.0)
Requires-Dist: requests (>=2.25.1,<3.0.0)
Project-URL: Repository, https://github.com/RYGhub/rygforms
